llm_fragments_pypi.py
llm_fragments_pypi-0.1.1.dist-info/METADATA
llm_fragments_pypi-0.1.1.dist-info/WHEEL
llm_fragments_pypi-0.1.1.dist-info/entry_points.txt
llm_fragments_pypi-0.1.1.dist-info/licenses/LICENSE
llm_fragments_pypi-0.1.1.dist-info/RECORD
