Metadata-Version: 2.4
Name: llm-fragments-pypi
Version: 0.1.1
Summary: LLM fragments plugin for PyPI packages metadata
Project-URL: Homepage, https://github.com/samueldg/llm-fragments-pypi
Project-URL: Repository, https://github.com/samueldg/llm-fragments-pypi
Project-URL: Changelog, https://github.com/samueldg/llm-fragments-pypi/releases
Project-URL: Issues, https://github.com/samueldg/llm-fragments-pypi/issues
Project-URL: CI, https://github.com/samueldg/llm-fragments-pypi/actions
Author: Samuel Dion-Girardeau
License: 
License-File: LICENSE
Keywords: llm,llm-fragments,pypi
Classifier: Development Status :: 4 - Beta
Classifier: Environment :: Console
Classifier: Environment :: Plugins
Classifier: Intended Audience :: Developers
Classifier: License :: OSI Approved :: Apache Software License
Classifier: Natural Language :: English
Classifier: Operating System :: OS Independent
Classifier: Programming Language :: Python
Classifier: Programming Language :: Python :: 3
Classifier: Programming Language :: Python :: 3 :: Only
Classifier: Programming Language :: Python :: 3.10
Classifier: Programming Language :: Python :: 3.11
Classifier: Programming Language :: Python :: 3.12
Classifier: Programming Language :: Python :: 3.13
Classifier: Topic :: Software Development :: Libraries :: Python Modules
Classifier: Topic :: Utilities
Classifier: Typing :: Typed
Requires-Python: >=3.10
Requires-Dist: httpx>=0.28.1
Requires-Dist: llm>=0.24
